[
  {"unit":"all", "date":"01-Sep-23", "day": "Fri", "value": 10030},
  {"unit":"all", "date":"02-Sep-23", "day": "Sat", "value": 11830},
  {"unit":"all", "date":"03-Sep-23", "day": "Sun", "value": 12037},
  {"unit":"all", "date":"04-Sep-23", "day": "Mon", "value": 13042},
  {"unit":"all", "date":"05-Sep-23", "day": "Tue", "value": 11024},
  {"unit":"all", "date":"06-Sep-23", "day": "Wed", "value": 12200},
  {"unit":"all", "date":"07-Sep-23", "day": "Thu", "value": 10403},
  {"unit":"all", "date":"08-Sep-23", "day": "Fri", "value": 11502},
  {"unit":"all", "date":"09-Sep-23", "day": "Sat", "value": 12235},
  {"unit":"all", "date":"10-Sep-23", "day": "Sun", "value": 10600},
  {"unit":"all", "date":"11-Sep-23", "day": "Mon", "value": 11502},
  {"unit":"all", "date":"12-Sep-23", "day": "Tue", "value": 11123},
  {"unit":"all", "date":"13-Sep-23", "day": "Wed", "value": 10076},
  {"unit":"all", "date":"14-Sep-23", "day": "Thu", "value": 11023},
  {"unit":"all", "date":"15-Sep-23", "day": "Fri", "value": 12026},
  {"unit":"all", "date":"16-Sep-23", "day": "Sat", "value": 11005},
  {"unit":"all", "date":"17-Sep-23", "day": "Sun", "value": 11029},
  {"unit":"all", "date":"18-Sep-23", "day": "Mon", "value": 11048},
  {"unit":"all", "date":"19-Sep-23", "day": "Tue", "value": 10973},
  {"unit":"all", "date":"20-Sep-23", "day": "Wed", "value": 10965},
  {"unit":"all", "date":"21-Sep-23", "day": "Thu", "value": 11142},
  {"unit":"all", "date":"22-Sep-23", "day": "Fri", "value": 12011},
  {"unit":"all", "date":"23-Sep-23", "day": "Sat", "value": 11009},
  {"unit":"all", "date":"24-Sep-23", "day": "Sun", "value": 12001},
  {"unit":"all", "date":"25-Sep-23", "day": "Mon", "value": 12540}
]
